didas/__init__.py
didas/_version.py
didas/mlflow.py
didas/oracle.py
didas-3.2.0.dist-info/METADATA
didas-3.2.0.dist-info/WHEEL
didas-3.2.0.dist-info/top_level.txt
didas-3.2.0.dist-info/RECORD
